{
    "model": {
        "type": "minecraft:select",
        "property": "minecraft:component",
        "component": "minecraft:custom_name",
        "cases": [
            {
                "when": ["Box (Medical Bay)", "Коробка (Медицинский Отсек)"],
                "model": {
                    "type": "minecraft:model",
                    "model": "mirrp:item/protocollockdown/boxes/deliverybox_cyan"
                }
            }
        ],
        "fallback": {
            "type": "minecraft:model",
            "model": "minecraft:item/diamond"
        }
    }
}