{
    "model": {
        "type": "minecraft:select",
        "property": "minecraft:component",
        "component": "minecraft:custom_name",
        "cases": [
            {
                "when": ["Spider", "Паучок"],
                "model": {
                    "type": "minecraft:model",
                    "model": "mrp:item/food/sweets/spider"
                }
            }
        ],
        "fallback": {
            "type": "minecraft:model",
            "model": "minecraft:item/spider_eye"
        }
    }
}